[
  {
    "ContainingType": "backend.Controllers.AuthController",
    "Method": "Auth",
    "RelativePath": "api/auth/{email}",
    "HttpMethod": "POST",
    "IsController": true,
    "Order": 0,
    "Parameters": [
      {
        "Name": "email",
        "Type": "System.String",
        "IsRequired": true
      }
    ],
    "ReturnTypes": []
  },
  {
    "ContainingType": "backend.Controllers.AuthController",
    "Method": "Logout",
    "RelativePath": "api/auth/{token}",
    "HttpMethod": "DELETE",
    "IsController": true,
    "Order": 0,
    "Parameters": [
      {
        "Name": "token",
        "Type": "System.String",
        "IsRequired": true
      }
    ],
    "ReturnTypes": []
  },
  {
    "ContainingType": "backend.Controllers.AuthController",
    "Method": "FetchUser",
    "RelativePath": "api/auth/{token}",
    "HttpMethod": "GET",
    "IsController": true,
    "Order": 0,
    "Parameters": [
      {
        "Name": "token",
        "Type": "System.String",
        "IsRequired": true
      }
    ],
    "ReturnTypes": [
      {
        "Type": "backend.Types.User",
        "MediaTypes": [
          "text/plain",
          "application/json",
          "text/json"
        ],
        "StatusCode": 200
      }
    ]
  },
  {
    "ContainingType": "backend.Controllers.AuthController",
    "Method": "Register",
    "RelativePath": "api/auth/reg",
    "HttpMethod": "POST",
    "IsController": true,
    "Order": 0,
    "Parameters": [
      {
        "Name": "data",
        "Type": "backend.Controllers.RegisterDto",
        "IsRequired": true
      }
    ],
    "ReturnTypes": []
  },
  {
    "ContainingType": "backend.Controllers.AuthController",
    "Method": "VerifyOtp",
    "RelativePath": "api/auth/verify",
    "HttpMethod": "POST",
    "IsController": true,
    "Order": 0,
    "Parameters": [
      {
        "Name": "data",
        "Type": "backend.Controllers.VerifyOtpDto",
        "IsRequired": true
      }
    ],
    "ReturnTypes": [
      {
        "Type": "backend.Types.Auth",
        "MediaTypes": [
          "text/plain",
          "application/json",
          "text/json"
        ],
        "StatusCode": 200
      }
    ]
  }
]